flask_session/__init__.py
flask_session/sessions.py
flask_session_custom-0.1.1.dist-info/LICENSE.rst
flask_session_custom-0.1.1.dist-info/METADATA
flask_session_custom-0.1.1.dist-info/WHEEL
flask_session_custom-0.1.1.dist-info/top_level.txt
flask_session_custom-0.1.1.dist-info/RECORD
