Metadata-Version: 2.1
Name: flask-session-custom
Version: 0.1.1
Summary: Your short project description here
Home-page: UNKNOWN
Author: Thang Tran
Author-email: thangtd1993@gmail.com
License: UNKNOWN
Platform: UNKNOWN
License-File: LICENSE.rst
Requires-Dist: flask (>=2.2)
Requires-Dist: cachelib
Requires-Dist: itsdangerous
Requires-Dist: Werkzeug
